README.md
pyproject.toml
setup.cfg
setup.py
orbital_transfer/__init__.py
orbital_transfer/api_client.py
orbital_transfer/api_response.py
orbital_transfer/configuration.py
orbital_transfer/exceptions.py
orbital_transfer/py.typed
orbital_transfer/rest.py
orbital_transfer.egg-info/PKG-INFO
orbital_transfer.egg-info/SOURCES.txt
orbital_transfer.egg-info/dependency_links.txt
orbital_transfer.egg-info/requires.txt
orbital_transfer.egg-info/top_level.txt
orbital_transfer/api/__init__.py
orbital_transfer/api/default_api.py
orbital_transfer/models/__init__.py
orbital_transfer/models/advanced_orbit_parameters.py
orbital_transfer/models/analytical_orbital_transfer_request.py
orbital_transfer/models/analytical_orbital_transfer_request_drag_perturbation.py
orbital_transfer/models/analytical_orbital_transfer_response.py
orbital_transfer/models/atmospheric_model.py
orbital_transfer/models/axis.py
orbital_transfer/models/body_solar_array.py
orbital_transfer/models/box_spacecraft_geometry.py
orbital_transfer/models/cartesian_ephemerides.py
orbital_transfer/models/circular_altitude_orbit_parameters.py
orbital_transfer/models/circular_ground_track_repeated_orbit_parameters.py
orbital_transfer/models/circular_orbit.py
orbital_transfer/models/circular_orbit_parameters.py
orbital_transfer/models/custom_maneuvering_strategy.py
orbital_transfer/models/deployable_fixed_solar_array.py
orbital_transfer/models/deployable_rotating_solar_array.py
orbital_transfer/models/drag_perturbation.py
orbital_transfer/models/duty_cycle_thrust_arc_definition.py
orbital_transfer/models/earth_potential_perturbation.py
orbital_transfer/models/elliptical_ground_track_repeated_eccentricity_orbit_parameters.py
orbital_transfer/models/elliptical_orbit.py
orbital_transfer/models/elliptical_orbit_parameters.py
orbital_transfer/models/elliptical_perigee_alt_apogee_alt_orbit_parameters.py
orbital_transfer/models/elliptical_perigee_alt_eccentricity_orbit_parameters.py
orbital_transfer/models/elliptical_sma_eccentricity_orbit_parameters.py
orbital_transfer/models/geostationary_orbit.py
orbital_transfer/models/harris_priester_atmospheric_model.py
orbital_transfer/models/keplerian_ephemerides.py
